slicesampling/__init__.py
slicesampling/sampler.py
slicesampling/univariate_sampler.py
slicesampling/version.py
slicesampling-0.1.5.dist-info/LICENSE
slicesampling-0.1.5.dist-info/METADATA
slicesampling-0.1.5.dist-info/WHEEL
slicesampling-0.1.5.dist-info/top_level.txt
slicesampling-0.1.5.dist-info/RECORD
