Metadata-Version: 2.1
Name: slicesampling
Version: 0.1.5
Summary: Set of Markov chain Monte Carlo (MCMC) sampling methods based on slice_sampler sampling
Home-page: https://code.ornl.gov/2kv/slicesampling
Author: Kris Villez
Author-email: villezk@ornl.gov
License: MIT
Platform: UNKNOWN
License-File: LICENSE
Requires-Dist: numpy
Requires-Dist: scipy
